SQcircuit/__init__.py
SQcircuit/circuit.py
SQcircuit/elements.py
SQcircuit/exceptions.py
SQcircuit/functions.py
SQcircuit/noise.py
SQcircuit/settings.py
SQcircuit/storage.py
SQcircuit/sweep.py
SQcircuit/symbolic.py
SQcircuit/systems.py
SQcircuit/texts.py
SQcircuit/torch_extensions.py
SQcircuit/units.py
SQcircuit/tests/__init__.py
SQcircuit/tests/conftest.py
SQcircuit/tests/test_descriptions.py
SQcircuit/tests/test_elements.py
SQcircuit/tests/test_elements_grad.py
SQcircuit/tests/test_functions.py
SQcircuit/tests/test_grad.py
SQcircuit/tests/test_noise.py
SQcircuit/tests/test_papers.py
SQcircuit/tests/test_phase_coord.py
SQcircuit/tests/test_qubit_grad.py
SQcircuit/tests/test_qubits.py
SQcircuit/tests/test_systems.py
SQcircuit/tests/data/descriptions/elements.txt
SQcircuit/tests/data/descriptions/flux_dist_all.txt
SQcircuit/tests/data/descriptions/flux_dist_inductors.txt
SQcircuit/tests/data/descriptions/flux_dist_junctions.txt
SQcircuit/tests/data/descriptions/zero_pi_inductors_ltx-a.txt
SQcircuit/tests/data/descriptions/zero_pi_inductors_ltx-b.txt
SQcircuit/tests/data/descriptions/zero_pi_inductors_txt-a.txt
SQcircuit/tests/data/descriptions/zero_pi_inductors_txt-b.txt
SQcircuit/tests/data/descriptions/zero_pi_junctions_ltx-a.txt
SQcircuit/tests/data/descriptions/zero_pi_junctions_ltx-b.txt
SQcircuit/tests/data/descriptions/zero_pi_junctions_txt-a.txt
SQcircuit/tests/data/descriptions/zero_pi_junctions_txt-b.txt
SQcircuit/tests/data/phase_coord/zeropi_0
SQcircuit/tests/data/phase_coord/zeropi_1
SQcircuit/tests/data/phase_coord/zeropi_paper_0.npy
SQcircuit/tests/data/phase_coord/zeropi_paper_1.npy
SQcircuit/tests/data/spectra/zeropi_paper.npy
SQcircuit-1.0.0.dist-info/LICENSE
SQcircuit-1.0.0.dist-info/METADATA
SQcircuit-1.0.0.dist-info/WHEEL
SQcircuit-1.0.0.dist-info/top_level.txt
SQcircuit-1.0.0.dist-info/RECORD
