Metadata-Version: 2.1
Name: SQcircuit
Version: 1.0.0
Summary: superconducting quantum circuit analyzer
Home-page: https://github.com/stanfordLINQS/SQcircuit
Author: Taha Rajabzadeh, Amir Safavi-Naeini
Author-email: tahar@stanford.edu, safavi@stanford.edu
License: BSD
Keywords: superconducting circuits
Classifier: Development Status :: 5 - Production/Stable
Classifier: License :: OSI Approved :: BSD License
Classifier: Programming Language :: Python :: 3
Classifier: Topic :: Scientific/Engineering
Classifier: Intended Audience :: Science/Research
Classifier: Operating System :: OS Independent
Requires-Python: >=3.6
License-File: LICENSE
Requires-Dist: numpy>=1.14.2
Requires-Dist: scipy>=1.1.0
Requires-Dist: matplotlib>=3.0.0
Requires-Dist: qutip>=5.0.0
Requires-Dist: dill>=0.3.4
Requires-Dist: IPython>=7.0.0
Requires-Dist: torch>=2.0
Requires-Dist: mpmath>=1.2.1
Requires-Dist: sympy>=1.13.0
